{
  "name": "Samir Bhowmik",
  "tagline": "Artist · Architect · Scholar",
  "credentials": "DA · M.Arch (UMD) · AIA · SAFA",
  "location": "Helsinki",
  "bio": "Samir Bhowmik is a Helsinki-based multidisciplinary artist, architect and scholar. He is an Academy of Finland Research Fellow (2022–27) at the University of the Arts Helsinki, where he explores extractivism and ecology through intelligent performance research in the Terra-Performing Project. He holds a Doctor of Arts (Aalto University, 2016) and a Master of Architecture (University of Maryland, 2003). His writing has appeared in Leonardo (MIT Press) and the Venice Architecture Biennale, and his work has been exhibited at the Helsinki Biennial, the Venice Architecture Biennale, and internationally.",
  "homeBio": "I make performance, installation, and moving image about the infrastructures beneath everyday life — energy, waste, memory, machines. Currently an Academy of Finland Research Fellow at Uniarts Helsinki.",
  "now": {
    "label": "Now",
    "text": "Speaking at [Event Name], [City] — [Month Year]",
    "url": "https://example.com/event",
    "date": "2026-06-01"
  },
  "links": {
    "youtube": "https://youtube.com/@your-handle",
    "vimeo": "https://vimeo.com/your-handle",
    "project": "https://www.uniarts.fi/en/projects/terra-performing/",
    "email": "you@example.com"
  },
  "social": {
    "linkedin": "https://www.linkedin.com/in/samirbhowmik",
    "instagram": "https://www.instagram.com/your-handle",
    "scholar": "https://scholar.google.com/citations?user=YOUR_ID",
    "orcid": "https://orcid.org/0000-0001-5830-614X"
  }
}
